README.md
setup.cfg
setup.py
roung_distributions/Binomialdistribution.py
roung_distributions/Gaussiandistribution.py
roung_distributions/Generaldistribution.py
roung_distributions/__init__.py
roung_distributions.egg-info/PKG-INFO
roung_distributions.egg-info/SOURCES.txt
roung_distributions.egg-info/dependency_links.txt
roung_distributions.egg-info/not-zip-safe
roung_distributions.egg-info/top_level.txt